SSRS/__init__.py
SSRS/schemas.py
pySSRS-1.0.0.dist-info/DESCRIPTION.rst
pySSRS-1.0.0.dist-info/METADATA
pySSRS-1.0.0.dist-info/RECORD
pySSRS-1.0.0.dist-info/WHEEL
pySSRS-1.0.0.dist-info/metadata.json
pySSRS-1.0.0.dist-info/top_level.txt
samples/FindItem.py
samples/GetParameters.py
samples/ListDir.py
samples/ListMethods.py
samples/LoadReport.py
samples/__init__.py
samples/connection_data.py
samples/context.py
