Metadata-Version: 2.0
Name: pySSRS
Version: 1.0.0
Summary: Python SSRS integrationusing SOAP RPCs
Home-page: https://github.com/FRReinert/PySSRS/
Author: Fabricio Roberto reinert
Author-email: fabricio.reinert@live.com
License: MIT license
Keywords: SSRS,Microsoft,Python,SOAP,RPC,Reporting,Services
Platform: UNKNOWN
Classifier: Development Status :: 2 - Pre-Alpha
Classifier: Intended Audience :: Developers
Classifier: License :: OSI Approved :: MIT License
Classifier: Natural Language :: English
Classifier: Programming Language :: Python :: 3.6
Requires-Dist: suds-py3
